exampledemoa/.DS_Store
exampledemoa/core/__init__.py
exampledemoa/core/quantization/__init__.py
exampledemoa/core/quantization/quantizer_kmeans.py
exampledemoa/core/quantization/torch_helpers.py
exampledemoa/core/quantization/vgg_model.py
exampledemoa/core/types/__init__.py
exampledemoa/core/types/binary_utils.py
exampledemoa/core/types/float_converter.py
exampledemoa/core/types/integer_converter.py
exampledemoa-0.0.2.dist-info/LICENSE
exampledemoa-0.0.2.dist-info/METADATA
exampledemoa-0.0.2.dist-info/WHEEL
exampledemoa-0.0.2.dist-info/RECORD
