Metadata-Version: 2.3
Name: exampledemoa
Version: 0.0.2
Summary: Basic test
Author: San Askaruly
Author-email: s.askaruly@gmail.com
Requires-Python: >=3.10
Classifier: Programming Language :: Python :: 3
Classifier: Programming Language :: Python :: 3.10
Classifier: Programming Language :: Python :: 3.11
Classifier: Programming Language :: Python :: 3.12
Classifier: Programming Language :: Python :: 3.13
Requires-Dist: fast-pytorch-kmeans (==0.2.2)
Requires-Dist: psutil (==7.0.0)
Requires-Dist: torch (==2.7.1)
Requires-Dist: torchaudio (==2.7.1)
Requires-Dist: torchvision (==0.22.1)
Requires-Dist: tqdm (==4.67.1)
